{
    "selected_at": "2026-05-14 21:16:47",
    "selection_metric": "f1",
    "git_commit_hash": "7f56826757521894fcbc08d20eaded803a21fb71",
    "best_experiment_row": {
        "experiment_id": "20260514_105614_zuha_01_efficientnet_b0_constrained_ep5_bs32_lr0p0001_basic",
        "timestamp": "20260514_105614",
        "runner": "zuha",
        "model_name": "01_efficientnet_b0",
        "run_type": "constrained",
        "epochs": 5,
        "batch_size": 32,
        "learning_rate": 0.0001,
        "optimizer": "adamw",
        "weight_decay": 0.0001,
        "scheduler": "none",
        "loss_function": "BCEWithLogitsLoss",
        "image_size": 224,
        "pretrained": true,
        "freeze_backbone": false,
        "augmentation_type": "basic",
        "seed": 42,
        "train_datasets_used": "corvi_latent_diffusion,wang_cnndetection_cnn_synth_test,wang_cnndetection_val",
        "evaluation_dataset": "dmimagedetect_test",
        "use_wang_train": false,
        "use_wang_val_as_train": true,
        "use_wang_test_as_train": false,
        "use_wang_cnn_synth_test_as_train": true,
        "use_corvi_train": true,
        "use_dmimagedetect_train": false,
        "use_realraise_train": false,
        "num_train_images": 18000,
        "num_eval_images": 8000,
        "real_train_count": 6006,
        "synthetic_train_count": 11994,
        "real_eval_count": 4000,
        "synthetic_eval_count": 4000,
        "best_epoch": 5,
        "best_val_loss": 1.161824141,
        "accuracy": 0.7255,
        "precision": 0.702423698,
        "recall": 0.7825,
        "f1": 0.740302744,
        "roc_auc": 0.7917095,
        "average_precision": 0.797840598,
        "eer": 0.26475,
        "threshold": 0.65,
        "tn": 2674,
        "fp": 1326,
        "fn": 870,
        "tp": 3130,
        "notes": "EfficientNet-B0 baseline with basic augmentation + added wang cnn synth test as train",
        "summary_csv_path": "d:\\Users\\DELL\\new-onedrive\\OneDrive - Institute of Business Administration\\IBA\\sem8\\genai\\competition\\outputs\\01_efficientnet_b0\\01_efficientnet_b0_summary.csv",
        "model_folder": "01_efficientnet_b0",
        "rank": 1
    },
    "extraction_results": {
        "best_model.pth": true,
        "config.json": true,
        "predictions.csv": true,
        "training_history.csv": true,
        "01_efficientnet_b0_summary.csv": true
    },
    "note": "Files were extracted from Git history. This is accurate only if the runner committed the model/config/predictions/history in the same commit as the summary row."
}